{
  "#type": "jv8:Array",
  "#value": [
    {
      "#type": "jcfg:DocumentObject.ПоступлениеТоваров",
      "#value": {
        "Ref": "75f2cf4e-cd77-11eb-9e1f-408d5c70a81d",
        "DeletionMark": false,
        "Date": "2021-06-15T16:03:42",
        "Number": "ЦБПТ-000653",
        "Posted": true,
        "Комментарий": "",
        "Ответственный": "ad22e671-29ed-11e9-9dd0-408d5c70a81d",
        "СуммаДокумента": 1431.4,
        "Магазин": "8b0747d8-38e6-11e6-99a1-001e67517e22",
        "ЦенаВключаетНДС": true,
        "УчитыватьНДС": true,
        "Контрагент": "8b4b6431-a862-11e5-b5e9-74d435e0817b",
        "Склад": "0ef7a55f-52df-11e6-be3d-74d435e0817b",
        "ЗаказПоставщику": "00000000-0000-0000-0000-000000000000",
        "ДатаВходящегоДокумента": "2021-06-15T00:00:00",
        "НомерВходящегоДокумента": "1165",
        "Организация": "6af083ae-946e-11e6-8014-408d5c72e23c",
        "БанковскийСчетКонтрагента": "00000000-0000-0000-0000-000000000000",
        "БанковскийСчетОрганизации": "00000000-0000-0000-0000-000000000000",
        "УдалитьБанковскийСчетОрганизации": "00000000-0000-0000-0000-000000000000",
        "ЕстьРасхождения": false,
        "ПредъявленСчетФактура": false,
        "НомерСчетаФактуры": "1165",
        "ДатаСчетаФактуры": "2021-06-15T00:00:00",
        "УдалитьПолученИзЕГАИС": false,
        "ТТНВходящаяЕГАИС": "00000000-0000-0000-0000-000000000000",
        "УдалитьАктПереданВЕГАИС": false,
        "ЕстьМаркируемаяПродукцияГИСМ": false,
        "ЕстьКиЗГИСМ": false,
        "ХозяйственнаяОперация": "ПоступлениеТоваров",
        "Договор": "00000000-0000-0000-0000-000000000000",
        "Товары": [
          {
            "Номенклатура": "0171b378-dcfe-11e4-8262-001e67517e23",
            "Характеристика": "00000000-0000-0000-0000-000000000000",
            "Количество": 1.02,
            "Цена": 192,
            "Сумма": 195.84,
            "СтавкаНДС": "НДС10",
            "СуммаНДС": 17.8,
            "КлючСвязиСерийныхНомеров": 0,
            "Упаковка": "00000000-0000-0000-0000-000000000000",
            "КоличествоУпаковок": 1.02,
            "СтатусУказанияСерий": 0,
            "ИдентификаторСтроки": "",
            "АлкогольнаяПродукция": "00000000-0000-0000-0000-000000000000",
            "ИдентификаторУпаковки": "",
            "КлючСвязи": 1,
            "НомерГТД": "00000000-0000-0000-0000-000000000000"
          },
          {
            "Номенклатура": "6ec6a336-3207-11e5-828f-001e67517e22",
            "Характеристика": "00000000-0000-0000-0000-000000000000",
            "Количество": 1.06,
            "Цена": 192,
            "Сумма": 203.52,
            "СтавкаНДС": "НДС10",
            "СуммаНДС": 18.5,
            "КлючСвязиСерийныхНомеров": 0,
            "Упаковка": "00000000-0000-0000-0000-000000000000",
            "КоличествоУпаковок": 1.06,
            "СтатусУказанияСерий": 0,
            "ИдентификаторСтроки": "",
            "АлкогольнаяПродукция": "00000000-0000-0000-0000-000000000000",
            "ИдентификаторУпаковки": "",
            "КлючСвязи": 2,
            "НомерГТД": "00000000-0000-0000-0000-000000000000"
          },
          {
            "Номенклатура": "0171b3d8-dcfe-11e4-8262-001e67517e23",
            "Характеристика": "00000000-0000-0000-0000-000000000000",
            "Количество": 1.11,
            "Цена": 459,
            "Сумма": 509.49,
            "СтавкаНДС": "НДС10",
            "СуммаНДС": 46.32,
            "КлючСвязиСерийныхНомеров": 0,
            "Упаковка": "00000000-0000-0000-0000-000000000000",
            "КоличествоУпаковок": 1.11,
            "СтатусУказанияСерий": 0,
            "ИдентификаторСтроки": "",
            "АлкогольнаяПродукция": "00000000-0000-0000-0000-000000000000",
            "ИдентификаторУпаковки": "",
            "КлючСвязи": 3,
            "НомерГТД": "00000000-0000-0000-0000-000000000000"
          },
          {
            "Номенклатура": "0171b3d7-dcfe-11e4-8262-001e67517e23",
            "Характеристика": "00000000-0000-0000-0000-000000000000",
            "Количество": 0.55,
            "Цена": 459,
            "Сумма": 252.45,
            "СтавкаНДС": "НДС10",
            "СуммаНДС": 22.95,
            "КлючСвязиСерийныхНомеров": 0,
            "Упаковка": "00000000-0000-0000-0000-000000000000",
            "КоличествоУпаковок": 0.55,
            "СтатусУказанияСерий": 0,
            "ИдентификаторСтроки": "",
            "АлкогольнаяПродукция": "00000000-0000-0000-0000-000000000000",
            "ИдентификаторУпаковки": "",
            "КлючСвязи": 4,
            "НомерГТД": "00000000-0000-0000-0000-000000000000"
          },
          {
            "Номенклатура": "0171b377-dcfe-11e4-8262-001e67517e23",
            "Характеристика": "00000000-0000-0000-0000-000000000000",
            "Количество": 0.73,
            "Цена": 370,
            "Сумма": 270.1,
            "СтавкаНДС": "НДС10",
            "СуммаНДС": 24.55,
            "КлючСвязиСерийныхНомеров": 0,
            "Упаковка": "00000000-0000-0000-0000-000000000000",
            "КоличествоУпаковок": 0.73,
            "СтатусУказанияСерий": 0,
            "ИдентификаторСтроки": "",
            "АлкогольнаяПродукция": "00000000-0000-0000-0000-000000000000",
            "ИдентификаторУпаковки": "",
            "КлючСвязи": 5,
            "НомерГТД": "00000000-0000-0000-0000-000000000000"
          }
        ],
        "ЭтапыОплат": [
          {
            "Сумма": 1431.4,
            "ДатаПлатежа": "2021-06-15T00:00:00",
            "Комментарий": "",
            "ОтсрочкаПлатежа": 0,
            "ВидПлатежа": "ОтсрочкаПлатежа",
            "ПроцентОплаты": 100,
            "ФормаОплаты": "Безналичная",
            "ДокументВзаимозачета": null
          }
        ]
      }
    },
    {
      "#type": "jcfg:DocumentObject.ПоступлениеТоваров",
      "#value": {
        "Ref": "579068d5-ce69-11eb-9e1f-408d5c70a81d",
        "DeletionMark": false,
        "Date": "2021-06-16T13:12:08",
        "Number": "ЦБПТ-000656",
        "Posted": true,
        "Комментарий": "",
        "Ответственный": "ad22e671-29ed-11e9-9dd0-408d5c70a81d",
        "СуммаДокумента": 5238.84,
        "Магазин": "8b0747d8-38e6-11e6-99a1-001e67517e22",
        "ЦенаВключаетНДС": true,
        "УчитыватьНДС": true,
        "Контрагент": "3ee47dbf-9102-11e6-94fe-74d435e0817b",
        "Склад": "0ef7a55f-52df-11e6-be3d-74d435e0817b",
        "ЗаказПоставщику": "00000000-0000-0000-0000-000000000000",
        "ДатаВходящегоДокумента": "2021-06-16T00:00:00",
        "НомерВходящегоДокумента": "33879",
        "Организация": "6af083ae-946e-11e6-8014-408d5c72e23c",
        "БанковскийСчетКонтрагента": "ddf2519a-9bec-11e6-9139-001517fbc48c",
        "БанковскийСчетОрганизации": "00000000-0000-0000-0000-000000000000",
        "УдалитьБанковскийСчетОрганизации": "00000000-0000-0000-0000-000000000000",
        "ЕстьРасхождения": false,
        "ПредъявленСчетФактура": false,
        "НомерСчетаФактуры": "33879",
        "ДатаСчетаФактуры": "2021-06-16T00:00:00",
        "УдалитьПолученИзЕГАИС": false,
        "ТТНВходящаяЕГАИС": "20417166-cd75-11eb-9e1f-408d5c70a81d",
        "УдалитьАктПереданВЕГАИС": false,
        "ЕстьМаркируемаяПродукцияГИСМ": false,
        "ЕстьКиЗГИСМ": false,
        "ХозяйственнаяОперация": "ПоступлениеТоваров",
        "Договор": "00000000-0000-0000-0000-000000000000",
        "Товары": [
          {
            "Номенклатура": "0786948b-dcfe-11e4-8262-001e67517e23",
            "Характеристика": "00000000-0000-0000-0000-000000000000",
            "Количество": 12,
            "Цена": 63.6,
            "Сумма": 763.2,
            "СтавкаНДС": "НДС20",
            "СуммаНДС": 127.2,
            "КлючСвязиСерийныхНомеров": 0,
            "Упаковка": "00000000-0000-0000-0000-000000000000",
            "КоличествоУпаковок": 12,
            "СтатусУказанияСерий": 0,
            "ИдентификаторСтроки": "1",
            "АлкогольнаяПродукция": "00000000-0000-0003-7022-000001230139",
            "ИдентификаторУпаковки": "",
            "КлючСвязи": 0,
            "НомерГТД": "00000000-0000-0000-0000-000000000000"
          },
          {
            "Номенклатура": "07869493-dcfe-11e4-8262-001e67517e23",
            "Характеристика": "00000000-0000-0000-0000-000000000000",
            "Количество": 12,
            "Цена": 63.6,
            "Сумма": 763.2,
            "СтавкаНДС": "НДС20",
            "СуммаНДС": 127.2,
            "КлючСвязиСерийныхНомеров": 0,
            "Упаковка": "00000000-0000-0000-0000-000000000000",
            "КоличествоУпаковок": 12,
            "СтатусУказанияСерий": 0,
            "ИдентификаторСтроки": "2",
            "АлкогольнаяПродукция": "00000000-0000-0003-7022-000001230136",
            "ИдентификаторУпаковки": "",
            "КлючСвязи": 0,
            "НомерГТД": "00000000-0000-0000-0000-000000000000"
          },
          {
            "Номенклатура": "078694a2-dcfe-11e4-8262-001e67517e23",
            "Характеристика": "00000000-0000-0000-0000-000000000000",
            "Количество": 12,
            "Цена": 46.31,
            "Сумма": 555.72,
            "СтавкаНДС": "НДС20",
            "СуммаНДС": 92.62,
            "КлючСвязиСерийныхНомеров": 0,
            "Упаковка": "00000000-0000-0000-0000-000000000000",
            "КоличествоУпаковок": 12,
            "СтатусУказанияСерий": 0,
            "ИдентификаторСтроки": "3",
            "АлкогольнаяПродукция": "00000000-0000-0003-7022-000001230150",
            "ИдентификаторУпаковки": "",
            "КлючСвязи": 0,
            "НомерГТД": "00000000-0000-0000-0000-000000000000"
          },
          {
            "Номенклатура": "078694a4-dcfe-11e4-8262-001e67517e23",
            "Характеристика": "00000000-0000-0000-0000-000000000000",
            "Количество": 12,
            "Цена": 49.62,
            "Сумма": 595.44,
            "СтавкаНДС": "НДС20",
            "СуммаНДС": 99.24,
            "КлючСвязиСерийныхНомеров": 0,
            "Упаковка": "00000000-0000-0000-0000-000000000000",
            "КоличествоУпаковок": 12,
            "СтатусУказанияСерий": 0,
            "ИдентификаторСтроки": "4",
            "АлкогольнаяПродукция": "00000000-0000-0003-7022-000001230434",
            "ИдентификаторУпаковки": "",
            "КлючСвязи": 0,
            "НомерГТД": "00000000-0000-0000-0000-000000000000"
          },
          {
            "Номенклатура": "078694a6-dcfe-11e4-8262-001e67517e23",
            "Характеристика": "00000000-0000-0000-0000-000000000000",
            "Количество": 12,
            "Цена": 48.93,
            "Сумма": 587.16,
            "СтавкаНДС": "НДС20",
            "СуммаНДС": 97.86,
            "КлючСвязиСерийныхНомеров": 0,
            "Упаковка": "00000000-0000-0000-0000-000000000000",
            "КоличествоУпаковок": 12,
            "СтатусУказанияСерий": 0,
            "ИдентификаторСтроки": "5",
            "АлкогольнаяПродукция": "00000000-0000-0003-7022-000001230120",
            "ИдентификаторУпаковки": "",
            "КлючСвязи": 0,
            "НомерГТД": "00000000-0000-0000-0000-000000000000"
          },
          {
            "Номенклатура": "17768786-555b-11e7-82a7-3497f6015b0a",
            "Характеристика": "00000000-0000-0000-0000-000000000000",
            "Количество": 24,
            "Цена": 57.79,
            "Сумма": 1386.96,
            "СтавкаНДС": "НДС20",
            "СуммаНДС": 231.16,
            "КлючСвязиСерийныхНомеров": 0,
            "Упаковка": "00000000-0000-0000-0000-000000000000",
            "КоличествоУпаковок": 24,
            "СтатусУказанияСерий": 0,
            "ИдентификаторСтроки": "6",
            "АлкогольнаяПродукция": "4c817123-ef71-47f4-dcaa-1e62017ea440",
            "ИдентификаторУпаковки": "",
            "КлючСвязи": 0,
            "НомерГТД": "00000000-0000-0000-0000-000000000000"
          },
          {
            "Номенклатура": "078694ac-dcfe-11e4-8262-001e67517e23",
            "Характеристика": "00000000-0000-0000-0000-000000000000",
            "Количество": 12,
            "Цена": 48.93,
            "Сумма": 587.16,
            "СтавкаНДС": "НДС20",
            "СуммаНДС": 97.86,
            "КлючСвязиСерийныхНомеров": 0,
            "Упаковка": "00000000-0000-0000-0000-000000000000",
            "КоличествоУпаковок": 12,
            "СтатусУказанияСерий": 0,
            "ИдентификаторСтроки": "7",
            "АлкогольнаяПродукция": "00000000-0000-0003-7022-000001230019",
            "ИдентификаторУпаковки": "",
            "КлючСвязи": 0,
            "НомерГТД": "00000000-0000-0000-0000-000000000000"
          }
        ],
        "ЭтапыОплат": [
          {
            "Сумма": 5238.84,
            "ДатаПлатежа": "2021-06-16T00:00:00",
            "Комментарий": "",
            "ОтсрочкаПлатежа": 0,
            "ВидПлатежа": "ОтсрочкаПлатежа",
            "ПроцентОплаты": 100,
            "ФормаОплаты": "Безналичная",
            "ДокументВзаимозачета": null
          }
        ]
      }
    }
  ]
}